generalpy/__init__.py
generalpy/_utils.py
generalpy/api.py
generalpy/cli.py
generalpy/ctypes.py
generalpy/custom_logging.py
generalpy/database.py
generalpy/decorator.py
generalpy/exceptions.py
generalpy/files.py
generalpy/general.py
generalpy/settings.py
generalpy/signal.py
generalpy-1.17.0.dist-info/METADATA
generalpy-1.17.0.dist-info/WHEEL
generalpy-1.17.0.dist-info/licenses/LICENSE
generalpy-1.17.0.dist-info/RECORD
