Metadata-Version: 2.3
Name: generalpy
Version: 1.17.0
Summary: Python package for general classes and methods
Project-URL: Homepage, https://github.com/sayyid5416/generalpy
Project-URL: Bug Tracker, https://github.com/sayyid5416/generalpy/issues
Author: sayyid5416
License-File: LICENSE
Classifier: License :: OSI Approved :: MIT License
Classifier: Operating System :: OS Independent
Classifier: Programming Language :: Python :: 3
Requires-Python: >=3.10
Requires-Dist: pytz
